MANIFEST.in
changelog.rst
documentation.rst
setup.py
todo.rst
brain/__init__.py
brain/connection.py
brain/data.py
brain/engine.py
brain/interface.py
brain/logic.py
brain/op.py
brain/xmlrpchelpers.py
brain/xmlrpclayer.py
brain.egg-info/PKG-INFO
brain.egg-info/SOURCES.txt
brain.egg-info/dependency_links.txt
brain.egg-info/top_level.txt
brain/test/__init__.py
brain/test/doc.py
brain/test/func.py
brain/test/fuzz.py
brain/test/helpers.py
brain/test/perf.py
brain/test/run.py
brain/test/internal/__init__.py
brain/test/internal/engine.py
brain/test/internal/interface.py
brain/test/public/__init__.py
brain/test/public/connection.py
brain/test/public/delete.py
brain/test/public/insert.py
brain/test/public/modify.py
brain/test/public/read.py
brain/test/public/requests.py
brain/test/public/search.py