Metadata-Version: 1.0
Name: brain
Version: 0.1.5
Summary: DDB front-end for SQL engines
Home-page: http://github.com/Manticore/brain
Author: Bogdan Opanchuk
Author-email: bg@bk.ru
License: UNKNOWN
Platform: UNKNOWN
Classifier: Development Status :: 4 - Beta
Classifier: Environment :: Console
Classifier: Intended Audience :: Developers
Classifier: License :: OSI Approved :: GNU General Public License (GPL)
Classifier: Operating System :: OS Independent
Classifier: Programming Language :: Python :: 3
Classifier: Topic :: Database :: Front-Ends
